.DS_Store
simplelayout/__init__.py
simplelayout/__main__.py
simplelayout/cli/__init__.py
simplelayout/cli/cli_generate.py
simplelayout/generator/__init__.py
simplelayout/generator/core.py
simplelayout/generator/utils.py
simplelayout_AnjaZhang-0.0.4.dist-info/LICENSE.txt
simplelayout_AnjaZhang-0.0.4.dist-info/METADATA
simplelayout_AnjaZhang-0.0.4.dist-info/WHEEL
simplelayout_AnjaZhang-0.0.4.dist-info/entry_points.txt
simplelayout_AnjaZhang-0.0.4.dist-info/top_level.txt
simplelayout_AnjaZhang-0.0.4.dist-info/RECORD
