Metadata-Version: 2.1
Name: simplelayout-AnjaZhang
Version: 0.0.4
Summary: A sample Python project
Home-page: https://github.com/idrl-assignment/3-simplelayout-package-AnjaZhang
Author: zhangxiaoya
Author-email: zhangxiaoya09@nudt.edu.cn
License: UNKNOWN
Platform: UNKNOWN
Classifier: Programming Language :: Python :: 3
Classifier: License :: OSI Approved :: MIT License
Classifier: Operating System :: OS Independent
Requires-Dist: numpy
Requires-Dist: matplotlib
Requires-Dist: scipy
Requires-Dist: pytest
